scityping/__init__.py
scityping/_version.py
scityping/base.py
scityping/base_types.py
scityping/functions.py
scityping/holoviews.py
scityping/json.py
scityping/numpy.py
scityping/pint.py
scityping/pydantic.py
scityping/quantities.py
scityping/scipy.py
scityping/torch.py
scityping/typing.py
scityping/utils.py
scityping/xarray.py
scityping/config/__init__.py
scityping/config/defaults.cfg
scityping-0.6.5.dist-info/LICENSE
scityping-0.6.5.dist-info/METADATA
scityping-0.6.5.dist-info/WHEEL
scityping-0.6.5.dist-info/top_level.txt
scityping-0.6.5.dist-info/RECORD
