Metadata-Version: 2.1
Name: scityping
Version: 0.6.5
Summary: Serializable data types for science applications
Author-email: Alexandre René <alex.c.rene@gmail.com>
License: MPL 2.0
Project-URL: Documentation, https://scityping.readthedocs.io/
Project-URL: Bug Tracker, https://github.com/alcrene/scityping/issues
Project-URL: Source, https://github.com/alcrene/scityping
Keywords: serialization,scientific computing,reproducibility
Classifier: Development Status :: 4 - Beta
Classifier: Intended Audience :: Science/Research
Classifier: License :: OSI Approved :: Mozilla Public License 2.0 (MPL 2.0)
Classifier: Programming Language :: Python :: 3
Classifier: Programming Language :: Python :: 3 :: Only
Classifier: Programming Language :: Python :: 3.8
Classifier: Programming Language :: Python :: 3.9
Classifier: Programming Language :: Python :: 3.10
Classifier: Programming Language :: Python :: 3.11
Classifier: Topic :: Scientific/Engineering
Classifier: Topic :: Scientific/Engineering :: Artificial Intelligence
Classifier: Typing :: Typed
Requires-Python: >=3.8
License-File: LICENSE
Requires-Dist: pydantic <2
Requires-Dist: valconfig
Provides-Extra: docs
Requires-Dist: sphinx ; extra == 'docs'
Requires-Dist: myst-parser ; extra == 'docs'
Requires-Dist: sphinx-book-theme ; extra == 'docs'
Requires-Dist: sphinxcontrib-mermaid ; extra == 'docs'
Requires-Dist: numpy ; extra == 'docs'
Requires-Dist: scipy ; extra == 'docs'
Requires-Dist: torch ; extra == 'docs'
Requires-Dist: pint ; extra == 'docs'
Requires-Dist: quantities ; extra == 'docs'
Provides-Extra: test
Requires-Dist: coverage ; extra == 'test'
Requires-Dist: pytest ; extra == 'test'
Requires-Dist: numpy ; extra == 'test'
Requires-Dist: scipy ; extra == 'test'
Requires-Dist: xarray ; extra == 'test'
Requires-Dist: torch ; extra == 'test'
Requires-Dist: blosc ; extra == 'test'
Requires-Dist: pint ; extra == 'test'
Requires-Dist: quantities ; extra == 'test'
Requires-Dist: netCDF4 ; extra == 'test'
